Metadata-Version: 2.1
Name: arslaanhttp
Version: 1.0.3
Summary: A simple HTTP server.
Home-page: 
Author: Arslaan Pathan
Author-email: xminecrafterfun@gmail.com
License: MIT
Keywords: http
License-File: LICENSE.txt
